oai_utils/__init__.py
oai_utils/openai_utils.py
oai_utils/py.typed
oai_utils/result.py
oai_utils/utils.py
oai_utils-0.1.dist-info/LICENSE
oai_utils-0.1.dist-info/METADATA
oai_utils-0.1.dist-info/WHEEL
oai_utils-0.1.dist-info/top_level.txt
oai_utils-0.1.dist-info/RECORD
