Metadata-Version: 2.1
Name: oai-utils
Version: 0.1
Summary: OpenAI Python Utils
Author-email: Rafal Wojdyla <ravwojdyla@gmail.com>
License: Apache License
Project-URL: repository, https://github.com/related-sciences/oai_utils
Keywords: openai
Classifier: Programming Language :: Python
Requires-Python: >=3.10
License-File: LICENSE
Requires-Dist: numpy (<2)
Requires-Dist: openai (<1)
Requires-Dist: tenacity (<9)
Requires-Dist: tiktoken (<1)
Requires-Dist: tqdm (<5)
Provides-Extra: dev
Requires-Dist: pre-commit (<4) ; extra == 'dev'
Requires-Dist: pytest (<8) ; extra == 'dev'
